{
  "endpoint": "intraday_history",
  "params": {
    "symbol": "159819",
    "period": "1",
    "start_date": "2026-04-28 09:30:00",
    "end_date": "2026-04-28 14:50:59",
    "adjust": ""
  },
  "fetched_at": "2026-04-28 14:50:43",
  "rows": [
    {
      "时间": "2026-04-28 09:30:00",
      "开盘": 1.753,
      "收盘": 1.753,
      "最高": 1.753,
      "最低": 1.753,
      "成交量": 7666,
      "成交额": 1343849.0,
      "均价": 1.753
    },
    {
      "时间": "2026-04-28 09:31:00",
      "开盘": 1.749,
      "收盘": 1.732,
      "最高": 1.749,
      "最低": 1.732,
      "成交量": 44635,
      "成交额": 7760502.0,
      "均价": 1.7408
    },
    {
      "时间": "2026-04-28 09:32:00",
      "开盘": 1.731,
      "收盘": 1.74,
      "最高": 1.741,
      "最低": 1.73,
      "成交量": 51010,
      "成交额": 8850424.0,
      "均价": 1.7379
    },
    {
      "时间": "2026-04-28 09:33:00",
      "开盘": 1.74,
      "收盘": 1.74,
      "最高": 1.743,
      "最低": 1.74,
      "成交量": 29365,
      "成交额": 5111655.0,
      "均价": 1.7386
    },
    {
      "时间": "2026-04-28 09:34:00",
      "开盘": 1.74,
      "收盘": 1.737,
      "最高": 1.74,
      "最低": 1.736,
      "成交量": 16890,
      "成交额": 2935381.0,
      "均价": 1.7385
    },
    {
      "时间": "2026-04-28 09:35:00",
      "开盘": 1.736,
      "收盘": 1.742,
      "最高": 1.743,
      "最低": 1.736,
      "成交量": 25376,
      "成交额": 4412879.0,
      "均价": 1.7386
    },
    {
      "时间": "2026-04-28 09:36:00",
      "开盘": 1.741,
      "收盘": 1.735,
      "最高": 1.742,
      "最低": 1.735,
      "成交量": 30706,
      "成交额": 5342731.0,
      "均价": 1.7388
    },
    {
      "时间": "2026-04-28 09:37:00",
      "开盘": 1.736,
      "收盘": 1.739,
      "最高": 1.74,
      "最低": 1.735,
      "成交量": 16239,
      "成交额": 2820734.0,
      "均价": 1.7386
    },
    {
      "时间": "2026-04-28 09:38:00",
      "开盘": 1.739,
      "收盘": 1.733,
      "最高": 1.739,
      "最低": 1.732,
      "成交量": 28654,
      "成交额": 4969518.0,
      "均价": 1.7381
    },
    {
      "时间": "2026-04-28 09:39:00",
      "开盘": 1.732,
      "收盘": 1.728,
      "最高": 1.732,
      "最低": 1.726,
      "成交量": 35249,
      "成交额": 6092996.0,
      "均价": 1.737
    },
    {
      "时间": "2026-04-28 09:40:00",
      "开盘": 1.727,
      "收盘": 1.728,
      "最高": 1.73,
      "最低": 1.727,
      "成交量": 38688,
      "成交额": 6686151.0,
      "均价": 1.7359
    },
    {
      "时间": "2026-04-28 09:41:00",
      "开盘": 1.73,
      "收盘": 1.737,
      "最高": 1.737,
      "最低": 1.728,
      "成交量": 41182,
      "成交额": 7133647.0,
      "均价": 1.7355
    },
    {
      "时间": "2026-04-28 09:42:00",
      "开盘": 1.737,
      "收盘": 1.738,
      "最高": 1.74,
      "最低": 1.737,
      "成交量": 8519,
      "成交额": 1481288.0,
      "均价": 1.7356
    },
    {
      "时间": "2026-04-28 09:43:00",
      "开盘": 1.737,
      "收盘": 1.739,
      "最高": 1.739,
      "最低": 1.737,
      "成交量": 18806,
      "成交额": 3269305.0,
      "均价": 1.7357
    },
    {
      "时间": "2026-04-28 09:44:00",
      "开盘": 1.739,
      "收盘": 1.742,
      "最高": 1.742,
      "最低": 1.739,
      "成交量": 28233,
      "成交额": 4914380.0,
      "均价": 1.736
    },
    {
      "时间": "2026-04-28 09:45:00",
      "开盘": 1.742,
      "收盘": 1.739,
      "最高": 1.742,
      "最低": 1.739,
      "成交量": 7544,
      "成交额": 1313029.0,
      "均价": 1.7361
    },
    {
      "时间": "2026-04-28 09:46:00",
      "开盘": 1.739,
      "收盘": 1.742,
      "最高": 1.742,
      "最低": 1.738,
      "成交量": 9844,
      "成交额": 1712511.0,
      "均价": 1.7362
    },
    {
      "时间": "2026-04-28 09:47:00",
      "开盘": 1.742,
      "收盘": 1.745,
      "最高": 1.745,
      "最低": 1.741,
      "成交量": 23070,
      "成交额": 4021423.0,
      "均价": 1.7366
    },
    {
      "时间": "2026-04-28 09:48:00",
      "开盘": 1.744,
      "收盘": 1.745,
      "最高": 1.746,
      "最低": 1.743,
      "成交量": 13797,
      "成交额": 2406888.0,
      "均价": 1.7368
    },
    {
      "时间": "2026-04-28 09:49:00",
      "开盘": 1.744,
      "收盘": 1.743,
      "最高": 1.745,
      "最低": 1.743,
      "成交量": 8976,
      "成交额": 1565026.0,
      "均价": 1.7369
    },
    {
      "时间": "2026-04-28 09:50:00",
      "开盘": 1.743,
      "收盘": 1.743,
      "最高": 1.744,
      "最低": 1.742,
      "成交量": 24400,
      "成交额": 4253799.0,
      "均价": 1.7372
    },
    {
      "时间": "2026-04-28 09:51:00",
      "开盘": 1.744,
      "收盘": 1.747,
      "最高": 1.748,
      "最低": 1.743,
      "成交量": 17723,
      "成交额": 3093855.0,
      "均价": 1.7375
    },
    {
      "时间": "2026-04-28 09:52:00",
      "开盘": 1.747,
      "收盘": 1.742,
      "最高": 1.748,
      "最低": 1.741,
      "成交量": 20076,
      "成交额": 3503530.0,
      "均价": 1.7378
    },
    {
      "时间": "2026-04-28 09:53:00",
      "开盘": 1.741,
      "收盘": 1.741,
      "最高": 1.742,
      "最低": 1.74,
      "成交量": 20509,
      "成交额": 3568964.0,
      "均价": 1.7379
    },
    {
      "时间": "2026-04-28 09:54:00",
      "开盘": 1.74,
      "收盘": 1.741,
      "最高": 1.742,
      "最低": 1.74,
      "成交量": 11253,
      "成交额": 1959177.0,
      "均价": 1.7379
    },
    {
      "时间": "2026-04-28 09:55:00",
      "开盘": 1.741,
      "收盘": 1.746,
      "最高": 1.746,
      "最低": 1.741,
      "成交量": 8247,
      "成交额": 1438849.0,
      "均价": 1.738
    },
    {
      "时间": "2026-04-28 09:56:00",
      "开盘": 1.748,
      "收盘": 1.746,
      "最高": 1.749,
      "最低": 1.746,
      "成交量": 13194,
      "成交额": 2305894.0,
      "均价": 1.7382
    },
    {
      "时间": "2026-04-28 09:57:00",
      "开盘": 1.747,
      "收盘": 1.746,
      "最高": 1.749,
      "最低": 1.746,
      "成交量": 5856,
      "成交额": 1023024.0,
      "均价": 1.7383
    },
    {
      "时间": "2026-04-28 09:58:00",
      "开盘": 1.746,
      "收盘": 1.745,
      "最高": 1.746,
      "最低": 1.743,
      "成交量": 5230,
      "成交额": 912496.0,
      "均价": 1.7384
    },
    {
      "时间": "2026-04-28 09:59:00",
      "开盘": 1.744,
      "收盘": 1.74,
      "最高": 1.744,
      "最低": 1.74,
      "成交量": 4553,
      "成交额": 792702.0,
      "均价": 1.7384
    },
    {
      "时间": "2026-04-28 10:00:00",
      "开盘": 1.74,
      "收盘": 1.742,
      "最高": 1.742,
      "最低": 1.739,
      "成交量": 10774,
      "成交额": 1875319.0,
      "均价": 1.7384
    },
    {
      "时间": "2026-04-28 10:01:00",
      "开盘": 1.742,
      "收盘": 1.738,
      "最高": 1.743,
      "最低": 1.738,
      "成交量": 10350,
      "成交额": 1800044.0,
      "均价": 1.7384
    },
    {
      "时间": "2026-04-28 10:02:00",
      "开盘": 1.738,
      "收盘": 1.737,
      "最高": 1.738,
      "最低": 1.736,
      "成交量": 11234,
      "成交额": 1950564.0,
      "均价": 1.7384
    },
    {
      "时间": "2026-04-28 10:03:00",
      "开盘": 1.737,
      "收盘": 1.735,
      "最高": 1.738,
      "最低": 1.735,
      "成交量": 4830,
      "成交额": 838707.0,
      "均价": 1.7384
    },
    {
      "时间": "2026-04-28 10:04:00",
      "开盘": 1.735,
      "收盘": 1.737,
      "最高": 1.737,
      "最低": 1.735,
      "成交量": 17835,
      "成交额": 3096481.0,
      "均价": 1.7383
    },
    {
      "时间": "2026-04-28 10:05:00",
      "开盘": 1.738,
      "收盘": 1.737,
      "最高": 1.739,
      "最低": 1.737,
      "成交量": 6902,
      "成交额": 1199307.0,
      "均价": 1.7383
    },
    {
      "时间": "2026-04-28 10:06:00",
      "开盘": 1.737,
      "收盘": 1.735,
      "最高": 1.737,
      "最低": 1.735,
      "成交量": 10767,
      "成交额": 1869522.0,
      "均价": 1.7383
    },
    {
      "时间": "2026-04-28 10:07:00",
      "开盘": 1.736,
      "收盘": 1.731,
      "最高": 1.736,
      "最低": 1.731,
      "成交量": 16895,
      "成交额": 2928313.0,
      "均价": 1.7382
    },
    {
      "时间": "2026-04-28 10:08:00",
      "开盘": 1.732,
      "收盘": 1.731,
      "最高": 1.732,
      "最低": 1.73,
      "成交量": 4477,
      "成交额": 774980.0,
      "均价": 1.7381
    },
    {
      "时间": "2026-04-28 10:09:00",
      "开盘": 1.73,
      "收盘": 1.73,
      "最高": 1.73,
      "最低": 1.729,
      "成交量": 22031,
      "成交额": 3810661.0,
      "均价": 1.7379
    },
    {
      "时间": "2026-04-28 10:10:00",
      "开盘": 1.73,
      "收盘": 1.728,
      "最高": 1.73,
      "最低": 1.728,
      "成交量": 3324,
      "成交额": 574684.0,
      "均价": 1.7378
    },
    {
      "时间": "2026-04-28 10:11:00",
      "开盘": 1.728,
      "收盘": 1.73,
      "最高": 1.73,
      "最低": 1.728,
      "成交量": 11147,
      "成交额": 1927511.0,
      "均价": 1.7377
    },
    {
      "时间": "2026-04-28 10:12:00",
      "开盘": 1.731,
      "收盘": 1.732,
      "最高": 1.733,
      "最低": 1.731,
      "成交量": 7538,
      "成交额": 1305446.0,
      "均价": 1.7376
    },
    {
      "时间": "2026-04-28 10:13:00",
      "开盘": 1.731,
      "收盘": 1.733,
      "最高": 1.733,
      "最低": 1.73,
      "成交量": 12138,
      "成交额": 2101306.0,
      "均价": 1.7375
    },
    {
      "时间": "2026-04-28 10:14:00",
      "开盘": 1.734,
      "收盘": 1.733,
      "最高": 1.734,
      "最低": 1.731,
      "成交量": 11539,
      "成交额": 1999205.0,
      "均价": 1.7375
    },
    {
      "时间": "2026-04-28 10:15:00",
      "开盘": 1.732,
      "收盘": 1.734,
      "最高": 1.734,
      "最低": 1.732,
      "成交量": 12752,
      "成交额": 2209875.0,
      "均价": 1.7374
    },
    {
      "时间": "2026-04-28 10:16:00",
      "开盘": 1.735,
      "收盘": 1.737,
      "最高": 1.737,
      "最低": 1.734,
      "成交量": 21416,
      "成交额": 3716278.0,
      "均价": 1.7373
    },
    {
      "时间": "2026-04-28 10:17:00",
      "开盘": 1.738,
      "收盘": 1.74,
      "最高": 1.74,
      "最低": 1.737,
      "成交量": 7883,
      "成交额": 1370462.0,
      "均价": 1.7374
    },
    {
      "时间": "2026-04-28 10:18:00",
      "开盘": 1.74,
      "收盘": 1.74,
      "最高": 1.742,
      "最低": 1.74,
      "成交量": 14123,
      "成交额": 2458942.0,
      "均价": 1.7374
    },
    {
      "时间": "2026-04-28 10:19:00",
      "开盘": 1.74,
      "收盘": 1.739,
      "最高": 1.74,
      "最低": 1.739,
      "成交量": 13164,
      "成交额": 2289751.0,
      "均价": 1.7374
    },
    {
      "时间": "2026-04-28 10:20:00",
      "开盘": 1.739,
      "收盘": 1.739,
      "最高": 1.739,
      "最低": 1.738,
      "成交量": 4326,
      "成交额": 751915.0,
      "均价": 1.7375
    },
    {
      "时间": "2026-04-28 10:21:00",
      "开盘": 1.739,
      "收盘": 1.738,
      "最高": 1.74,
      "最低": 1.737,
      "成交量": 13674,
      "成交额": 2376724.0,
      "均价": 1.7375
    },
    {
      "时间": "2026-04-28 10:22:00",
      "开盘": 1.738,
      "收盘": 1.735,
      "最高": 1.738,
      "最低": 1.735,
      "成交量": 10443,
      "成交额": 1814024.0,
      "均价": 1.7375
    },
    {
      "时间": "2026-04-28 10:23:00",
      "开盘": 1.735,
      "收盘": 1.735,
      "最高": 1.735,
      "最低": 1.734,
      "成交量": 6876,
      "成交额": 1192365.0,
      "均价": 1.7374
    },
    {
      "时间": "2026-04-28 10:24:00",
      "开盘": 1.735,
      "收盘": 1.734,
      "最高": 1.735,
      "最低": 1.733,
      "成交量": 3899,
      "成交额": 675975.0,
      "均价": 1.7374
    },
    {
      "时间": "2026-04-28 10:25:00",
      "开盘": 1.733,
      "收盘": 1.734,
      "最高": 1.735,
      "最低": 1.733,
      "成交量": 5891,
      "成交额": 1021477.0,
      "均价": 1.7374
    },
    {
      "时间": "2026-04-28 10:26:00",
      "开盘": 1.734,
      "收盘": 1.738,
      "最高": 1.738,
      "最低": 1.734,
      "成交量": 13394,
      "成交额": 2325844.0,
      "均价": 1.7374
    },
    {
      "时间": "2026-04-28 10:27:00",
      "开盘": 1.738,
      "收盘": 1.738,
      "最高": 1.739,
      "最低": 1.737,
      "成交量": 19175,
      "成交额": 3332633.0,
      "均价": 1.7374
    },
    {
      "时间": "2026-04-28 10:28:00",
      "开盘": 1.738,
      "收盘": 1.74,
      "最高": 1.74,
      "最低": 1.738,
      "成交量": 4060,
      "成交额": 705952.0,
      "均价": 1.7374
    },
    {
      "时间": "2026-04-28 10:29:00",
      "开盘": 1.74,
      "收盘": 1.738,
      "最高": 1.74,
      "最低": 1.738,
      "成交量": 3557,
      "成交额": 618436.0,
      "均价": 1.7374
    },
    {
      "时间": "2026-04-28 10:30:00",
      "开盘": 1.739,
      "收盘": 1.738,
      "最高": 1.739,
      "最低": 1.738,
      "成交量": 7891,
      "成交额": 1371686.0,
      "均价": 1.7374
    },
    {
      "时间": "2026-04-28 10:31:00",
      "开盘": 1.739,
      "收盘": 1.737,
      "最高": 1.739,
      "最低": 1.736,
      "成交量": 6849,
      "成交额": 1189663.0,
      "均价": 1.7374
    },
    {
      "时间": "2026-04-28 10:32:00",
      "开盘": 1.736,
      "收盘": 1.733,
      "最高": 1.737,
      "最低": 1.733,
      "成交量": 28840,
      "成交额": 5004225.0,
      "均价": 1.7373
    },
    {
      "时间": "2026-04-28 10:33:00",
      "开盘": 1.733,
      "收盘": 1.733,
      "最高": 1.733,
      "最低": 1.732,
      "成交量": 12776,
      "成交额": 2212927.0,
      "均价": 1.7373
    },
    {
      "时间": "2026-04-28 10:34:00",
      "开盘": 1.734,
      "收盘": 1.733,
      "最高": 1.735,
      "最低": 1.732,
      "成交量": 13121,
      "成交额": 2274948.0,
      "均价": 1.7372
    },
    {
      "时间": "2026-04-28 10:35:00",
      "开盘": 1.733,
      "收盘": 1.732,
      "最高": 1.734,
      "最低": 1.732,
      "成交量": 3694,
      "成交额": 639854.0,
      "均价": 1.7372
    },
    {
      "时间": "2026-04-28 10:36:00",
      "开盘": 1.732,
      "收盘": 1.733,
      "最高": 1.733,
      "最低": 1.731,
      "成交量": 8906,
      "成交额": 1542864.0,
      "均价": 1.7372
    },
    {
      "时间": "2026-04-28 10:37:00",
      "开盘": 1.733,
      "收盘": 1.731,
      "最高": 1.733,
      "最低": 1.731,
      "成交量": 3606,
      "成交额": 624626.0,
      "均价": 1.7372
    },
    {
      "时间": "2026-04-28 10:38:00",
      "开盘": 1.731,
      "收盘": 1.73,
      "最高": 1.732,
      "最低": 1.73,
      "成交量": 10900,
      "成交额": 1886479.0,
      "均价": 1.7371
    },
    {
      "时间": "2026-04-28 10:39:00",
      "开盘": 1.73,
      "收盘": 1.729,
      "最高": 1.73,
      "最低": 1.729,
      "成交量": 13277,
      "成交额": 2296403.0,
      "均价": 1.737
    },
    {
      "时间": "2026-04-28 10:40:00",
      "开盘": 1.729,
      "收盘": 1.729,
      "最高": 1.73,
      "最低": 1.728,
      "成交量": 5711,
      "成交额": 987339.0,
      "均价": 1.7369
    },
    {
      "时间": "2026-04-28 10:41:00",
      "开盘": 1.73,
      "收盘": 1.733,
      "最高": 1.733,
      "最低": 1.729,
      "成交量": 7149,
      "成交额": 1237683.0,
      "均价": 1.7369
    },
    {
      "时间": "2026-04-28 10:42:00",
      "开盘": 1.733,
      "收盘": 1.734,
      "最高": 1.734,
      "最低": 1.732,
      "成交量": 3736,
      "成交额": 647475.0,
      "均价": 1.7369
    },
    {
      "时间": "2026-04-28 10:43:00",
      "开盘": 1.733,
      "收盘": 1.738,
      "最高": 1.738,
      "最低": 1.733,
      "成交量": 19688,
      "成交额": 3418147.0,
      "均价": 1.7369
    },
    {
      "时间": "2026-04-28 10:44:00",
      "开盘": 1.738,
      "收盘": 1.739,
      "最高": 1.74,
      "最低": 1.738,
      "成交量": 8082,
      "成交额": 1405641.0,
      "均价": 1.7369
    },
    {
      "时间": "2026-04-28 10:45:00",
      "开盘": 1.739,
      "收盘": 1.738,
      "最高": 1.739,
      "最低": 1.735,
      "成交量": 18785,
      "成交额": 3262122.0,
      "均价": 1.7369
    },
    {
      "时间": "2026-04-28 10:46:00",
      "开盘": 1.738,
      "收盘": 1.738,
      "最高": 1.739,
      "最低": 1.738,
      "成交量": 4047,
      "成交额": 703636.0,
      "均价": 1.7369
    },
    {
      "时间": "2026-04-28 10:47:00",
      "开盘": 1.738,
      "收盘": 1.738,
      "最高": 1.738,
      "最低": 1.737,
      "成交量": 5220,
      "成交额": 907182.0,
      "均价": 1.7369
    },
    {
      "时间": "2026-04-28 10:48:00",
      "开盘": 1.739,
      "收盘": 1.736,
      "最高": 1.739,
      "最低": 1.736,
      "成交量": 15096,
      "成交额": 2622472.0,
      "均价": 1.7369
    },
    {
      "时间": "2026-04-28 10:49:00",
      "开盘": 1.736,
      "收盘": 1.735,
      "最高": 1.737,
      "最低": 1.735,
      "成交量": 3150,
      "成交额": 546838.0,
      "均价": 1.7369
    },
    {
      "时间": "2026-04-28 10:50:00",
      "开盘": 1.735,
      "收盘": 1.734,
      "最高": 1.736,
      "最低": 1.733,
      "成交量": 4396,
      "成交额": 762572.0,
      "均价": 1.7369
    },
    {
      "时间": "2026-04-28 10:51:00",
      "开盘": 1.735,
      "收盘": 1.735,
      "最高": 1.736,
      "最低": 1.735,
      "成交量": 7272,
      "成交额": 1262208.0,
      "均价": 1.7369
    },
    {
      "时间": "2026-04-28 10:52:00",
      "开盘": 1.735,
      "收盘": 1.736,
      "最高": 1.737,
      "最低": 1.735,
      "成交量": 4711,
      "成交额": 818019.0,
      "均价": 1.7369
    },
    {
      "时间": "2026-04-28 10:53:00",
      "开盘": 1.736,
      "收盘": 1.738,
      "最高": 1.738,
      "最低": 1.736,
      "成交量": 6667,
      "成交额": 1157932.0,
      "均价": 1.7369
    },
    {
      "时间": "2026-04-28 10:54:00",
      "开盘": 1.738,
      "收盘": 1.738,
      "最高": 1.739,
      "最低": 1.737,
      "成交量": 5417,
      "成交额": 941658.0,
      "均价": 1.7369
    },
    {
      "时间": "2026-04-28 10:55:00",
      "开盘": 1.738,
      "收盘": 1.738,
      "最高": 1.738,
      "最低": 1.737,
      "成交量": 4896,
      "成交额": 850466.0,
      "均价": 1.7369
    },
    {
      "时间": "2026-04-28 10:56:00",
      "开盘": 1.737,
      "收盘": 1.736,
      "最高": 1.737,
      "最低": 1.735,
      "成交量": 2773,
      "成交额": 481605.0,
      "均价": 1.7369
    },
    {
      "时间": "2026-04-28 10:57:00",
      "开盘": 1.736,
      "收盘": 1.735,
      "最高": 1.736,
      "最低": 1.734,
      "成交量": 11278,
      "成交额": 1956968.0,
      "均价": 1.7369
    },
    {
      "时间": "2026-04-28 10:58:00",
      "开盘": 1.735,
      "收盘": 1.734,
      "最高": 1.735,
      "最低": 1.734,
      "成交量": 1217,
      "成交额": 211044.0,
      "均价": 1.7369
    },
    {
      "时间": "2026-04-28 10:59:00",
      "开盘": 1.735,
      "收盘": 1.735,
      "最高": 1.736,
      "最低": 1.734,
      "成交量": 13522,
      "成交额": 2346091.0,
      "均价": 1.7369
    },
    {
      "时间": "2026-04-28 11:00:00",
      "开盘": 1.735,
      "收盘": 1.736,
      "最高": 1.737,
      "最低": 1.735,
      "成交量": 8930,
      "成交额": 1550419.0,
      "均价": 1.7368
    },
    {
      "时间": "2026-04-28 11:01:00",
      "开盘": 1.738,
      "收盘": 1.738,
      "最高": 1.738,
      "最低": 1.736,
      "成交量": 5130,
      "成交额": 891184.0,
      "均价": 1.7368
    },
    {
      "时间": "2026-04-28 11:02:00",
      "开盘": 1.738,
      "收盘": 1.737,
      "最高": 1.738,
      "最低": 1.736,
      "成交量": 3880,
      "成交额": 673922.0,
      "均价": 1.7368
    },
    {
      "时间": "2026-04-28 11:03:00",
      "开盘": 1.737,
      "收盘": 1.735,
      "最高": 1.737,
      "最低": 1.733,
      "成交量": 47492,
      "成交额": 8242296.0,
      "均价": 1.7368
    },
    {
      "时间": "2026-04-28 11:04:00",
      "开盘": 1.735,
      "收盘": 1.735,
      "最高": 1.737,
      "最低": 1.734,
      "成交量": 10289,
      "成交额": 1785020.0,
      "均价": 1.7368
    },
    {
      "时间": "2026-04-28 11:05:00",
      "开盘": 1.735,
      "收盘": 1.736,
      "最高": 1.736,
      "最低": 1.734,
      "成交量": 7080,
      "成交额": 1228485.0,
      "均价": 1.7368
    },
    {
      "时间": "2026-04-28 11:06:00",
      "开盘": 1.736,
      "收盘": 1.739,
      "最高": 1.739,
      "最低": 1.736,
      "成交量": 8111,
      "成交额": 1409875.0,
      "均价": 1.7368
    },
    {
      "时间": "2026-04-28 11:07:00",
      "开盘": 1.74,
      "收盘": 1.74,
      "最高": 1.74,
      "最低": 1.738,
      "成交量": 12273,
      "成交额": 2134232.0,
      "均价": 1.7368
    },
    {
      "时间": "2026-04-28 11:08:00",
      "开盘": 1.739,
      "收盘": 1.739,
      "最高": 1.74,
      "最低": 1.738,
      "成交量": 3774,
      "成交额": 656242.0,
      "均价": 1.7368
    },
    {
      "时间": "2026-04-28 11:09:00",
      "开盘": 1.739,
      "收盘": 1.74,
      "最高": 1.741,
      "最低": 1.739,
      "成交量": 10347,
      "成交额": 1800520.0,
      "均价": 1.7368
    },
    {
      "时间": "2026-04-28 11:10:00",
      "开盘": 1.74,
      "收盘": 1.738,
      "最高": 1.74,
      "最低": 1.737,
      "成交量": 18213,
      "成交额": 3166434.0,
      "均价": 1.7369
    },
    {
      "时间": "2026-04-28 11:11:00",
      "开盘": 1.738,
      "收盘": 1.737,
      "最高": 1.738,
      "最低": 1.737,
      "成交量": 1485,
      "成交额": 257976.0,
      "均价": 1.7369
    },
    {
      "时间": "2026-04-28 11:12:00",
      "开盘": 1.738,
      "收盘": 1.735,
      "最高": 1.738,
      "最低": 1.735,
      "成交量": 8146,
      "成交额": 1413987.0,
      "均价": 1.7369
    },
    {
      "时间": "2026-04-28 11:13:00",
      "开盘": 1.735,
      "收盘": 1.736,
      "最高": 1.736,
      "最低": 1.735,
      "成交量": 7444,
      "成交额": 1292023.0,
      "均价": 1.7368
    },
    {
      "时间": "2026-04-28 11:14:00",
      "开盘": 1.736,
      "收盘": 1.738,
      "最高": 1.738,
      "最低": 1.736,
      "成交量": 2715,
      "成交额": 471435.0,
      "均价": 1.7368
    },
    {
      "时间": "2026-04-28 11:15:00",
      "开盘": 1.738,
      "收盘": 1.737,
      "最高": 1.738,
      "最低": 1.736,
      "成交量": 8820,
      "成交额": 1532116.0,
      "均价": 1.7368
    },
    {
      "时间": "2026-04-28 11:16:00",
      "开盘": 1.737,
      "收盘": 1.738,
      "最高": 1.739,
      "最低": 1.737,
      "成交量": 8558,
      "成交额": 1487601.0,
      "均价": 1.7369
    },
    {
      "时间": "2026-04-28 11:17:00",
      "开盘": 1.738,
      "收盘": 1.735,
      "最高": 1.738,
      "最低": 1.735,
      "成交量": 11054,
      "成交额": 1919291.0,
      "均价": 1.7369
    },
    {
      "时间": "2026-04-28 11:18:00",
      "开盘": 1.735,
      "收盘": 1.736,
      "最高": 1.737,
      "最低": 1.735,
      "成交量": 4987,
      "成交额": 865738.0,
      "均价": 1.7368
    },
    {
      "时间": "2026-04-28 11:19:00",
      "开盘": 1.737,
      "收盘": 1.741,
      "最高": 1.741,
      "最低": 1.737,
      "成交量": 7621,
      "成交额": 1325960.0,
      "均价": 1.7369
    },
    {
      "时间": "2026-04-28 11:20:00",
      "开盘": 1.74,
      "收盘": 1.743,
      "最高": 1.743,
      "最低": 1.74,
      "成交量": 13645,
      "成交额": 2376612.0,
      "均价": 1.7369
    },
    {
      "时间": "2026-04-28 11:21:00",
      "开盘": 1.743,
      "收盘": 1.742,
      "最高": 1.744,
      "最低": 1.742,
      "成交量": 11562,
      "成交额": 2014983.0,
      "均价": 1.737
    },
    {
      "时间": "2026-04-28 11:22:00",
      "开盘": 1.742,
      "收盘": 1.743,
      "最高": 1.743,
      "最低": 1.742,
      "成交量": 8612,
      "成交额": 1500314.0,
      "均价": 1.737
    },
    {
      "时间": "2026-04-28 11:23:00",
      "开盘": 1.743,
      "收盘": 1.742,
      "最高": 1.744,
      "最低": 1.742,
      "成交量": 6411,
      "成交额": 1117352.0,
      "均价": 1.737
    },
    {
      "时间": "2026-04-28 11:24:00",
      "开盘": 1.742,
      "收盘": 1.743,
      "最高": 1.743,
      "最低": 1.742,
      "成交量": 9441,
      "成交额": 1645100.0,
      "均价": 1.7371
    },
    {
      "时间": "2026-04-28 11:25:00",
      "开盘": 1.742,
      "收盘": 1.742,
      "最高": 1.743,
      "最低": 1.742,
      "成交量": 3613,
      "成交额": 629647.0,
      "均价": 1.7371
    },
    {
      "时间": "2026-04-28 11:26:00",
      "开盘": 1.743,
      "收盘": 1.744,
      "最高": 1.745,
      "最低": 1.743,
      "成交量": 11700,
      "成交额": 2039724.0,
      "均价": 1.7371
    },
    {
      "时间": "2026-04-28 11:27:00",
      "开盘": 1.744,
      "收盘": 1.743,
      "最高": 1.745,
      "最低": 1.743,
      "成交量": 6228,
      "成交额": 1086243.0,
      "均价": 1.7371
    },
    {
      "时间": "2026-04-28 11:28:00",
      "开盘": 1.744,
      "收盘": 1.745,
      "最高": 1.746,
      "最低": 1.744,
      "成交量": 8722,
      "成交额": 1522274.0,
      "均价": 1.7372
    },
    {
      "时间": "2026-04-28 11:29:00",
      "开盘": 1.747,
      "收盘": 1.746,
      "最高": 1.748,
      "最低": 1.746,
      "成交量": 6733,
      "成交额": 1175957.0,
      "均价": 1.7372
    },
    {
      "时间": "2026-04-28 11:30:00",
      "开盘": 1.746,
      "收盘": 1.746,
      "最高": 1.748,
      "最低": 1.746,
      "成交量": 5681,
      "成交额": 992523.0,
      "均价": 1.7373
    },
    {
      "时间": "2026-04-28 13:01:00",
      "开盘": 1.746,
      "收盘": 1.747,
      "最高": 1.751,
      "最低": 1.746,
      "成交量": 42320,
      "成交额": 7400443.0,
      "均价": 1.7376
    },
    {
      "时间": "2026-04-28 13:02:00",
      "开盘": 1.746,
      "收盘": 1.747,
      "最高": 1.749,
      "最低": 1.746,
      "成交量": 5236,
      "成交额": 915013.0,
      "均价": 1.7376
    },
    {
      "时间": "2026-04-28 13:03:00",
      "开盘": 1.747,
      "收盘": 1.744,
      "最高": 1.748,
      "最低": 1.744,
      "成交量": 7674,
      "成交额": 1340293.0,
      "均价": 1.7377
    },
    {
      "时间": "2026-04-28 13:04:00",
      "开盘": 1.744,
      "收盘": 1.745,
      "最高": 1.746,
      "最低": 1.743,
      "成交量": 14099,
      "成交额": 2458411.0,
      "均价": 1.7377
    },
    {
      "时间": "2026-04-28 13:05:00",
      "开盘": 1.746,
      "收盘": 1.744,
      "最高": 1.746,
      "最低": 1.744,
      "成交量": 1749,
      "成交额": 305089.0,
      "均价": 1.7377
    },
    {
      "时间": "2026-04-28 13:06:00",
      "开盘": 1.744,
      "收盘": 1.744,
      "最高": 1.746,
      "最低": 1.744,
      "成交量": 10666,
      "成交额": 1860958.0,
      "均价": 1.7378
    },
    {
      "时间": "2026-04-28 13:07:00",
      "开盘": 1.744,
      "收盘": 1.741,
      "最高": 1.744,
      "最低": 1.741,
      "成交量": 9040,
      "成交额": 1574955.0,
      "均价": 1.7378
    },
    {
      "时间": "2026-04-28 13:08:00",
      "开盘": 1.741,
      "收盘": 1.742,
      "最高": 1.743,
      "最低": 1.741,
      "成交量": 6023,
      "成交额": 1048894.0,
      "均价": 1.7378
    },
    {
      "时间": "2026-04-28 13:09:00",
      "开盘": 1.742,
      "收盘": 1.739,
      "最高": 1.742,
      "最低": 1.739,
      "成交量": 33961,
      "成交额": 5913539.0,
      "均价": 1.7379
    },
    {
      "时间": "2026-04-28 13:10:00",
      "开盘": 1.739,
      "收盘": 1.74,
      "最高": 1.74,
      "最低": 1.738,
      "成交量": 2918,
      "成交额": 507385.0,
      "均价": 1.7379
    },
    {
      "时间": "2026-04-28 13:11:00",
      "开盘": 1.74,
      "收盘": 1.738,
      "最高": 1.74,
      "最低": 1.738,
      "成交量": 8954,
      "成交额": 1557025.0,
      "均价": 1.7379
    },
    {
      "时间": "2026-04-28 13:12:00",
      "开盘": 1.738,
      "收盘": 1.738,
      "最高": 1.739,
      "最低": 1.738,
      "成交量": 3596,
      "成交额": 625005.0,
      "均价": 1.7379
    },
    {
      "时间": "2026-04-28 13:13:00",
      "开盘": 1.738,
      "收盘": 1.737,
      "最高": 1.738,
      "最低": 1.737,
      "成交量": 25410,
      "成交额": 4415795.0,
      "均价": 1.7379
    },
    {
      "时间": "2026-04-28 13:14:00",
      "开盘": 1.737,
      "收盘": 1.737,
      "最高": 1.737,
      "最低": 1.736,
      "成交量": 2017,
      "成交额": 350245.0,
      "均价": 1.7379
    },
    {
      "时间": "2026-04-28 13:15:00",
      "开盘": 1.737,
      "收盘": 1.738,
      "最高": 1.738,
      "最低": 1.736,
      "成交量": 7356,
      "成交额": 1277730.0,
      "均价": 1.7379
    },
    {
      "时间": "2026-04-28 13:16:00",
      "开盘": 1.736,
      "收盘": 1.735,
      "最高": 1.736,
      "最低": 1.734,
      "成交量": 6738,
      "成交额": 1168915.0,
      "均价": 1.7379
    },
    {
      "时间": "2026-04-28 13:17:00",
      "开盘": 1.734,
      "收盘": 1.736,
      "最高": 1.736,
      "最低": 1.734,
      "成交量": 4849,
      "成交额": 841519.0,
      "均价": 1.7379
    },
    {
      "时间": "2026-04-28 13:18:00",
      "开盘": 1.736,
      "收盘": 1.736,
      "最高": 1.736,
      "最低": 1.735,
      "成交量": 7634,
      "成交额": 1325225.0,
      "均价": 1.7379
    },
    {
      "时间": "2026-04-28 13:19:00",
      "开盘": 1.735,
      "收盘": 1.736,
      "最高": 1.737,
      "最低": 1.735,
      "成交量": 6807,
      "成交额": 1181500.0,
      "均价": 1.7379
    },
    {
      "时间": "2026-04-28 13:20:00",
      "开盘": 1.736,
      "收盘": 1.735,
      "最高": 1.736,
      "最低": 1.735,
      "成交量": 3414,
      "成交额": 592571.0,
      "均价": 1.7379
    },
    {
      "时间": "2026-04-28 13:21:00",
      "开盘": 1.735,
      "收盘": 1.736,
      "最高": 1.736,
      "最低": 1.735,
      "成交量": 6765,
      "成交额": 1174292.0,
      "均价": 1.7378
    },
    {
      "时间": "2026-04-28 13:22:00",
      "开盘": 1.737,
      "收盘": 1.738,
      "最高": 1.738,
      "最低": 1.736,
      "成交量": 6355,
      "成交额": 1103932.0,
      "均价": 1.7378
    },
    {
      "时间": "2026-04-28 13:23:00",
      "开盘": 1.738,
      "收盘": 1.738,
      "最高": 1.739,
      "最低": 1.737,
      "成交量": 1763,
      "成交额": 306457.0,
      "均价": 1.7378
    },
    {
      "时间": "2026-04-28 13:24:00",
      "开盘": 1.738,
      "收盘": 1.737,
      "最高": 1.74,
      "最低": 1.736,
      "成交量": 19199,
      "成交额": 3336859.0,
      "均价": 1.7378
    },
    {
      "时间": "2026-04-28 13:25:00",
      "开盘": 1.737,
      "收盘": 1.737,
      "最高": 1.737,
      "最低": 1.736,
      "成交量": 16812,
      "成交额": 2920218.0,
      "均价": 1.7378
    },
    {
      "时间": "2026-04-28 13:26:00",
      "开盘": 1.737,
      "收盘": 1.738,
      "最高": 1.738,
      "最低": 1.737,
      "成交量": 7042,
      "成交额": 1223583.0,
      "均价": 1.7378
    },
    {
      "时间": "2026-04-28 13:27:00",
      "开盘": 1.737,
      "收盘": 1.737,
      "最高": 1.737,
      "最低": 1.736,
      "成交量": 5631,
      "成交额": 977944.0,
      "均价": 1.7378
    },
    {
      "时间": "2026-04-28 13:28:00",
      "开盘": 1.737,
      "收盘": 1.737,
      "最高": 1.738,
      "最低": 1.737,
      "成交量": 13178,
      "成交额": 2290146.0,
      "均价": 1.7378
    },
    {
      "时间": "2026-04-28 13:29:00",
      "开盘": 1.737,
      "收盘": 1.737,
      "最高": 1.738,
      "最低": 1.737,
      "成交量": 13390,
      "成交额": 2326021.0,
      "均价": 1.7378
    },
    {
      "时间": "2026-04-28 13:30:00",
      "开盘": 1.737,
      "收盘": 1.737,
      "最高": 1.738,
      "最低": 1.737,
      "成交量": 3461,
      "成交额": 601363.0,
      "均价": 1.7378
    },
    {
      "时间": "2026-04-28 13:31:00",
      "开盘": 1.737,
      "收盘": 1.735,
      "最高": 1.738,
      "最低": 1.735,
      "成交量": 39317,
      "成交额": 6828208.0,
      "均价": 1.7378
    },
    {
      "时间": "2026-04-28 13:32:00",
      "开盘": 1.735,
      "收盘": 1.735,
      "最高": 1.737,
      "最低": 1.735,
      "成交量": 14196,
      "成交额": 2464356.0,
      "均价": 1.7378
    },
    {
      "时间": "2026-04-28 13:33:00",
      "开盘": 1.736,
      "收盘": 1.736,
      "最高": 1.736,
      "最低": 1.735,
      "成交量": 11937,
      "成交额": 2072132.0,
      "均价": 1.7378
    },
    {
      "时间": "2026-04-28 13:34:00",
      "开盘": 1.736,
      "收盘": 1.735,
      "最高": 1.736,
      "最低": 1.735,
      "成交量": 12603,
      "成交额": 2186662.0,
      "均价": 1.7378
    },
    {
      "时间": "2026-04-28 13:35:00",
      "开盘": 1.736,
      "收盘": 1.734,
      "最高": 1.736,
      "最低": 1.734,
      "成交量": 18538,
      "成交额": 3215913.0,
      "均价": 1.7377
    },
    {
      "时间": "2026-04-28 13:36:00",
      "开盘": 1.734,
      "收盘": 1.733,
      "最高": 1.735,
      "最低": 1.733,
      "成交量": 8071,
      "成交额": 1399225.0,
      "均价": 1.7377
    },
    {
      "时间": "2026-04-28 13:37:00",
      "开盘": 1.733,
      "收盘": 1.731,
      "最高": 1.733,
      "最低": 1.73,
      "成交量": 14656,
      "成交额": 2538122.0,
      "均价": 1.7377
    },
    {
      "时间": "2026-04-28 13:38:00",
      "开盘": 1.731,
      "收盘": 1.73,
      "最高": 1.732,
      "最低": 1.73,
      "成交量": 6150,
      "成交额": 1064454.0,
      "均价": 1.7376
    },
    {
      "时间": "2026-04-28 13:39:00",
      "开盘": 1.73,
      "收盘": 1.73,
      "最高": 1.731,
      "最低": 1.73,
      "成交量": 25509,
      "成交额": 4413115.0,
      "均价": 1.7375
    },
    {
      "时间": "2026-04-28 13:40:00",
      "开盘": 1.73,
      "收盘": 1.732,
      "最高": 1.732,
      "最低": 1.73,
      "成交量": 8395,
      "成交额": 1453147.0,
      "均价": 1.7375
    },
    {
      "时间": "2026-04-28 13:41:00",
      "开盘": 1.732,
      "收盘": 1.73,
      "最高": 1.732,
      "最低": 1.73,
      "成交量": 11855,
      "成交额": 2051757.0,
      "均价": 1.7375
    },
    {
      "时间": "2026-04-28 13:42:00",
      "开盘": 1.731,
      "收盘": 1.733,
      "最高": 1.735,
      "最低": 1.731,
      "成交量": 3242,
      "成交额": 562088.0,
      "均价": 1.7375
    },
    {
      "时间": "2026-04-28 13:43:00",
      "开盘": 1.733,
      "收盘": 1.733,
      "最高": 1.734,
      "最低": 1.733,
      "成交量": 7301,
      "成交额": 1265650.0,
      "均价": 1.7375
    },
    {
      "时间": "2026-04-28 13:44:00",
      "开盘": 1.733,
      "收盘": 1.732,
      "最高": 1.733,
      "最低": 1.731,
      "成交量": 3967,
      "成交额": 687009.0,
      "均价": 1.7374
    },
    {
      "时间": "2026-04-28 13:45:00",
      "开盘": 1.731,
      "收盘": 1.731,
      "最高": 1.732,
      "最低": 1.731,
      "成交量": 4277,
      "成交额": 740562.0,
      "均价": 1.7374
    },
    {
      "时间": "2026-04-28 13:46:00",
      "开盘": 1.732,
      "收盘": 1.731,
      "最高": 1.732,
      "最低": 1.73,
      "成交量": 5890,
      "成交额": 1019590.0,
      "均价": 1.7374
    },
    {
      "时间": "2026-04-28 13:47:00",
      "开盘": 1.731,
      "收盘": 1.732,
      "最高": 1.733,
      "最低": 1.731,
      "成交量": 4407,
      "成交额": 763296.0,
      "均价": 1.7374
    },
    {
      "时间": "2026-04-28 13:48:00",
      "开盘": 1.732,
      "收盘": 1.732,
      "最高": 1.733,
      "最低": 1.731,
      "成交量": 3284,
      "成交额": 568784.0,
      "均价": 1.7374
    },
    {
      "时间": "2026-04-28 13:49:00",
      "开盘": 1.732,
      "收盘": 1.732,
      "最高": 1.733,
      "最低": 1.731,
      "成交量": 3725,
      "成交额": 645140.0,
      "均价": 1.7374
    },
    {
      "时间": "2026-04-28 13:50:00",
      "开盘": 1.732,
      "收盘": 1.731,
      "最高": 1.732,
      "最低": 1.73,
      "成交量": 19260,
      "成交额": 3332916.0,
      "均价": 1.7373
    },
    {
      "时间": "2026-04-28 13:51:00",
      "开盘": 1.731,
      "收盘": 1.728,
      "最高": 1.731,
      "最低": 1.728,
      "成交量": 24141,
      "成交额": 4173635.0,
      "均价": 1.7372
    },
    {
      "时间": "2026-04-28 13:52:00",
      "开盘": 1.729,
      "收盘": 1.728,
      "最高": 1.729,
      "最低": 1.727,
      "成交量": 48917,
      "成交额": 8454392.0,
      "均价": 1.737
    },
    {
      "时间": "2026-04-28 13:53:00",
      "开盘": 1.728,
      "收盘": 1.728,
      "最高": 1.728,
      "最低": 1.727,
      "成交量": 7378,
      "成交额": 1274247.0,
      "均价": 1.737
    },
    {
      "时间": "2026-04-28 13:54:00",
      "开盘": 1.727,
      "收盘": 1.727,
      "最高": 1.728,
      "最低": 1.727,
      "成交量": 7344,
      "成交额": 1268625.0,
      "均价": 1.7369
    },
    {
      "时间": "2026-04-28 13:55:00",
      "开盘": 1.728,
      "收盘": 1.729,
      "最高": 1.729,
      "最低": 1.727,
      "成交量": 6417,
      "成交额": 1108651.0,
      "均价": 1.7369
    },
    {
      "时间": "2026-04-28 13:56:00",
      "开盘": 1.729,
      "收盘": 1.729,
      "最高": 1.73,
      "最低": 1.728,
      "成交量": 9660,
      "成交额": 1670432.0,
      "均价": 1.7369
    },
    {
      "时间": "2026-04-28 13:57:00",
      "开盘": 1.729,
      "收盘": 1.729,
      "最高": 1.73,
      "最低": 1.728,
      "成交量": 5113,
      "成交额": 883697.0,
      "均价": 1.7369
    },
    {
      "时间": "2026-04-28 13:58:00",
      "开盘": 1.729,
      "收盘": 1.727,
      "最高": 1.729,
      "最低": 1.727,
      "成交量": 14150,
      "成交额": 2444014.0,
      "均价": 1.7368
    },
    {
      "时间": "2026-04-28 13:59:00",
      "开盘": 1.726,
      "收盘": 1.729,
      "最高": 1.729,
      "最低": 1.726,
      "成交量": 23274,
      "成交额": 4019161.0,
      "均价": 1.7367
    },
    {
      "时间": "2026-04-28 14:00:00",
      "开盘": 1.729,
      "收盘": 1.728,
      "最高": 1.729,
      "最低": 1.727,
      "成交量": 4829,
      "成交额": 834244.0,
      "均价": 1.7367
    },
    {
      "时间": "2026-04-28 14:01:00",
      "开盘": 1.728,
      "收盘": 1.728,
      "最高": 1.728,
      "最低": 1.727,
      "成交量": 6077,
      "成交额": 1049842.0,
      "均价": 1.7366
    },
    {
      "时间": "2026-04-28 14:02:00",
      "开盘": 1.728,
      "收盘": 1.728,
      "最高": 1.729,
      "最低": 1.727,
      "成交量": 7765,
      "成交额": 1341693.0,
      "均价": 1.7366
    },
    {
      "时间": "2026-04-28 14:03:00",
      "开盘": 1.727,
      "收盘": 1.729,
      "最高": 1.729,
      "最低": 1.727,
      "成交量": 5008,
      "成交额": 864985.0,
      "均价": 1.7366
    },
    {
      "时间": "2026-04-28 14:04:00",
      "开盘": 1.729,
      "收盘": 1.727,
      "最高": 1.729,
      "最低": 1.726,
      "成交量": 6861,
      "成交额": 1185111.0,
      "均价": 1.7366
    },
    {
      "时间": "2026-04-28 14:05:00",
      "开盘": 1.726,
      "收盘": 1.728,
      "最高": 1.729,
      "最低": 1.726,
      "成交量": 10591,
      "成交额": 1829140.0,
      "均价": 1.7365
    },
    {
      "时间": "2026-04-28 14:06:00",
      "开盘": 1.729,
      "收盘": 1.729,
      "最高": 1.729,
      "最低": 1.728,
      "成交量": 3237,
      "成交额": 559418.0,
      "均价": 1.7365
    },
    {
      "时间": "2026-04-28 14:07:00",
      "开盘": 1.729,
      "收盘": 1.727,
      "最高": 1.729,
      "最低": 1.726,
      "成交量": 11064,
      "成交额": 1911234.0,
      "均价": 1.7364
    },
    {
      "时间": "2026-04-28 14:08:00",
      "开盘": 1.727,
      "收盘": 1.728,
      "最高": 1.728,
      "最低": 1.726,
      "成交量": 7610,
      "成交额": 1313940.0,
      "均价": 1.7364
    },
    {
      "时间": "2026-04-28 14:09:00",
      "开盘": 1.729,
      "收盘": 1.729,
      "最高": 1.73,
      "最低": 1.727,
      "成交量": 6019,
      "成交额": 1040056.0,
      "均价": 1.7364
    },
    {
      "时间": "2026-04-28 14:10:00",
      "开盘": 1.729,
      "收盘": 1.73,
      "最高": 1.73,
      "最低": 1.728,
      "成交量": 6199,
      "成交额": 1071959.0,
      "均价": 1.7364
    },
    {
      "时间": "2026-04-28 14:11:00",
      "开盘": 1.729,
      "收盘": 1.728,
      "最高": 1.73,
      "最低": 1.728,
      "成交量": 10906,
      "成交额": 1885648.0,
      "均价": 1.7363
    },
    {
      "时间": "2026-04-28 14:12:00",
      "开盘": 1.727,
      "收盘": 1.73,
      "最高": 1.73,
      "最低": 1.727,
      "成交量": 6912,
      "成交额": 1194596.0,
      "均价": 1.7363
    },
    {
      "时间": "2026-04-28 14:13:00",
      "开盘": 1.731,
      "收盘": 1.731,
      "最高": 1.732,
      "最低": 1.73,
      "成交量": 5606,
      "成交额": 970476.0,
      "均价": 1.7363
    },
    {
      "时间": "2026-04-28 14:14:00",
      "开盘": 1.731,
      "收盘": 1.732,
      "最高": 1.732,
      "最低": 1.73,
      "成交量": 6337,
      "成交额": 1097087.0,
      "均价": 1.7363
    },
    {
      "时间": "2026-04-28 14:15:00",
      "开盘": 1.732,
      "收盘": 1.73,
      "最高": 1.732,
      "最低": 1.73,
      "成交量": 3997,
      "成交额": 691754.0,
      "均价": 1.7363
    },
    {
      "时间": "2026-04-28 14:16:00",
      "开盘": 1.73,
      "收盘": 1.73,
      "最高": 1.731,
      "最低": 1.73,
      "成交量": 13097,
      "成交额": 2265752.0,
      "均价": 1.7362
    },
    {
      "时间": "2026-04-28 14:17:00",
      "开盘": 1.728,
      "收盘": 1.729,
      "最高": 1.73,
      "最低": 1.728,
      "成交量": 8055,
      "成交额": 1392592.0,
      "均价": 1.7362
    },
    {
      "时间": "2026-04-28 14:18:00",
      "开盘": 1.729,
      "收盘": 1.726,
      "最高": 1.729,
      "最低": 1.726,
      "成交量": 13685,
      "成交额": 2364877.0,
      "均价": 1.7362
    },
    {
      "时间": "2026-04-28 14:19:00",
      "开盘": 1.727,
      "收盘": 1.725,
      "最高": 1.727,
      "最低": 1.725,
      "成交量": 33478,
      "成交额": 5778340.0,
      "均价": 1.736
    },
    {
      "时间": "2026-04-28 14:20:00",
      "开盘": 1.726,
      "收盘": 1.725,
      "最高": 1.726,
      "最低": 1.724,
      "成交量": 18349,
      "成交额": 3165211.0,
      "均价": 1.7359
    },
    {
      "时间": "2026-04-28 14:21:00",
      "开盘": 1.725,
      "收盘": 1.724,
      "最高": 1.725,
      "最低": 1.723,
      "成交量": 14740,
      "成交额": 2541199.0,
      "均价": 1.7359
    },
    {
      "时间": "2026-04-28 14:22:00",
      "开盘": 1.724,
      "收盘": 1.723,
      "最高": 1.724,
      "最低": 1.722,
      "成交量": 8880,
      "成交额": 1529966.0,
      "均价": 1.7358
    },
    {
      "时间": "2026-04-28 14:23:00",
      "开盘": 1.723,
      "收盘": 1.723,
      "最高": 1.724,
      "最低": 1.722,
      "成交量": 28726,
      "成交额": 4949310.0,
      "均价": 1.7357
    },
    {
      "时间": "2026-04-28 14:24:00",
      "开盘": 1.722,
      "收盘": 1.723,
      "最高": 1.723,
      "最低": 1.721,
      "成交量": 27831,
      "成交额": 4792306.0,
      "均价": 1.7355
    },
    {
      "时间": "2026-04-28 14:25:00",
      "开盘": 1.723,
      "收盘": 1.721,
      "最高": 1.723,
      "最低": 1.721,
      "成交量": 17224,
      "成交额": 2964880.0,
      "均价": 1.7354
    },
    {
      "时间": "2026-04-28 14:26:00",
      "开盘": 1.721,
      "收盘": 1.721,
      "最高": 1.721,
      "最低": 1.72,
      "成交量": 21117,
      "成交额": 3632796.0,
      "均价": 1.7353
    },
    {
      "时间": "2026-04-28 14:27:00",
      "开盘": 1.72,
      "收盘": 1.72,
      "最高": 1.721,
      "最低": 1.72,
      "成交量": 23226,
      "成交额": 3995067.0,
      "均价": 1.7351
    },
    {
      "时间": "2026-04-28 14:28:00",
      "开盘": 1.72,
      "收盘": 1.719,
      "最高": 1.72,
      "最低": 1.719,
      "成交量": 12739,
      "成交额": 2190166.0,
      "均价": 1.7351
    },
    {
      "时间": "2026-04-28 14:29:00",
      "开盘": 1.719,
      "收盘": 1.721,
      "最高": 1.721,
      "最低": 1.719,
      "成交量": 29280,
      "成交额": 5035663.0,
      "均价": 1.7349
    },
    {
      "时间": "2026-04-28 14:30:00",
      "开盘": 1.721,
      "收盘": 1.719,
      "最高": 1.721,
      "最低": 1.719,
      "成交量": 19008,
      "成交额": 3268701.0,
      "均价": 1.7348
    },
    {
      "时间": "2026-04-28 14:31:00",
      "开盘": 1.719,
      "收盘": 1.72,
      "最高": 1.72,
      "最低": 1.718,
      "成交量": 30856,
      "成交额": 5303664.0,
      "均价": 1.7346
    },
    {
      "时间": "2026-04-28 14:32:00",
      "开盘": 1.72,
      "收盘": 1.717,
      "最高": 1.72,
      "最低": 1.717,
      "成交量": 24997,
      "成交额": 4295925.0,
      "均价": 1.7344
    },
    {
      "时间": "2026-04-28 14:33:00",
      "开盘": 1.718,
      "收盘": 1.718,
      "最高": 1.719,
      "最低": 1.717,
      "成交量": 27292,
      "成交额": 4688307.0,
      "均价": 1.7342
    },
    {
      "时间": "2026-04-28 14:34:00",
      "开盘": 1.718,
      "收盘": 1.717,
      "最高": 1.718,
      "最低": 1.716,
      "成交量": 13098,
      "成交额": 2248910.0,
      "均价": 1.7342
    },
    {
      "时间": "2026-04-28 14:35:00",
      "开盘": 1.717,
      "收盘": 1.716,
      "最高": 1.717,
      "最低": 1.715,
      "成交量": 22177,
      "成交额": 3804784.0,
      "均价": 1.734
    },
    {
      "时间": "2026-04-28 14:36:00",
      "开盘": 1.715,
      "收盘": 1.715,
      "最高": 1.716,
      "最低": 1.714,
      "成交量": 21475,
      "成交额": 3682842.0,
      "均价": 1.7339
    },
    {
      "时间": "2026-04-28 14:37:00",
      "开盘": 1.715,
      "收盘": 1.716,
      "最高": 1.717,
      "最低": 1.715,
      "成交量": 41628,
      "成交额": 7138327.0,
      "均价": 1.7336
    },
    {
      "时间": "2026-04-28 14:38:00",
      "开盘": 1.717,
      "收盘": 1.72,
      "最高": 1.72,
      "最低": 1.716,
      "成交量": 24508,
      "成交额": 4209087.0,
      "均价": 1.7334
    },
    {
      "时间": "2026-04-28 14:39:00",
      "开盘": 1.72,
      "收盘": 1.72,
      "最高": 1.72,
      "最低": 1.718,
      "成交量": 18214,
      "成交额": 3130173.0,
      "均价": 1.7333
    },
    {
      "时间": "2026-04-28 14:40:00",
      "开盘": 1.72,
      "收盘": 1.719,
      "最高": 1.72,
      "最低": 1.718,
      "成交量": 17067,
      "成交额": 2933007.0,
      "均价": 1.7332
    },
    {
      "时间": "2026-04-28 14:41:00",
      "开盘": 1.719,
      "收盘": 1.719,
      "最高": 1.72,
      "最低": 1.718,
      "成交量": 19895,
      "成交额": 3419830.0,
      "均价": 1.7331
    },
    {
      "时间": "2026-04-28 14:42:00",
      "开盘": 1.718,
      "收盘": 1.718,
      "最高": 1.719,
      "最低": 1.717,
      "成交量": 21525,
      "成交额": 3697130.0,
      "均价": 1.733
    },
    {
      "时间": "2026-04-28 14:43:00",
      "开盘": 1.718,
      "收盘": 1.717,
      "最高": 1.719,
      "最低": 1.717,
      "成交量": 18707,
      "成交额": 3212614.0,
      "均价": 1.7329
    },
    {
      "时间": "2026-04-28 14:44:00",
      "开盘": 1.717,
      "收盘": 1.719,
      "最高": 1.72,
      "最低": 1.717,
      "成交量": 16020,
      "成交额": 2753753.0,
      "均价": 1.7328
    },
    {
      "时间": "2026-04-28 14:45:00",
      "开盘": 1.719,
      "收盘": 1.721,
      "最高": 1.721,
      "最低": 1.719,
      "成交量": 33845,
      "成交额": 5820935.0,
      "均价": 1.7327
    },
    {
      "时间": "2026-04-28 14:46:00",
      "开盘": 1.721,
      "收盘": 1.724,
      "最高": 1.725,
      "最低": 1.721,
      "成交量": 22724,
      "成交额": 3915009.0,
      "均价": 1.7326
    },
    {
      "时间": "2026-04-28 14:47:00",
      "开盘": 1.724,
      "收盘": 1.723,
      "最高": 1.724,
      "最低": 1.723,
      "成交量": 37226,
      "成交额": 6414030.0,
      "均价": 1.7325
    },
    {
      "时间": "2026-04-28 14:48:00",
      "开盘": 1.723,
      "收盘": 1.721,
      "最高": 1.723,
      "最低": 1.721,
      "成交量": 40415,
      "成交额": 6959428.0,
      "均价": 1.7324
    },
    {
      "时间": "2026-04-28 14:49:00",
      "开盘": 1.721,
      "收盘": 1.72,
      "最高": 1.722,
      "最低": 1.72,
      "成交量": 17706,
      "成交额": 3047227.0,
      "均价": 1.7323
    },
    {
      "时间": "2026-04-28 14:50:00",
      "开盘": 1.72,
      "收盘": 1.722,
      "最高": 1.722,
      "最低": 1.72,
      "成交量": 51257,
      "成交额": 8820202.0,
      "均价": 1.7321
    }
  ]
}